{
  "arch": "x86_64",
  "llvm-target": "x86_64-unknown-none",
  "data-layout": "e-m:e-i8:8:32-i16:16:32-i64:64-i128:128-n32:64-S128",
  "features": "-mmx,-sse,+soft-float",
  "target-endian": "little",
  "target-pointer-width": "64",
  "target-c-int-width": "32",

  "relocation-model": "static",
  "function-sections": true,
  "eh-frame-header": false,
  "code-model": "small",
  
  "linker": "rust-lld",
  "linker-flavor": "ld.lld",
  "linker-is-gnu": true,
  "pre-link-args":            {
    "ld.lld": ["-T./x86_64-unknown-none.lds"]
  },


  "os": "none",
  "panic-strategy": "abort",
  "disable-redzone": true
}